{
    "categories": [
        {
            "name": "Yarn",
            "subcategories": [
                {
                    "name": "New Colors",
                    "url": "https://www.crochet.com/yarn/new-colors/c/500132"
                },
                {
                    "name": "Newest Yarn Lines",
                    "url": "https://www.crochet.com/yarn/newest-yarn-lines/c/500112"
                },
                {
                    "name": "Berroco Yarns",
                    "url": "https://www.crochet.com/yarn/berrocco/c/50011803"
                },
                {
                    "name": "Lion Brand Yarns",
                    "url": "https://www.crochet.com/yarn/lion-brand/c/50011802"
                },
                {
                    "name": "Yarn Value Packs",
                    "url": "https://www.crochet.com/yarn/yarn-value-packs/c/500123"
                },
                {
                    "name": "View All",
                    "url": "https://www.crochet.com/yarn/view-all-yarns/c/500198"
                }
            ]
        },
        {
            "name": "Kits & Bundles",
            "subcategories": [
                {
                    "name": "Beginner Kits",
                    "url": "https://www.crochet.com/kits/beginner-kits/c/500801"
                },
                {
                    "name": "Looops Crochet  Amigurumi Kits",
                    "url": "https://www.crochet.com/kits/looops-crochet-amigurumi-kits/c/500805"
                },
                {
                    "name": "Project Bundles",
                    "url": "https://www.crochet.com/kits/project-bundles/c/500822"
                },
                {
                    "name": "View All",
                    "url": "https://www.crochet.com/kits/view-all/c/500819"
                }
            ]
        },
        {
            "name": "Hooks",
            "subcategories": [
                {
                    "name": "New",
                    "url": "https://www.crochet.com/hooks/new/c/500307"
                },
                {
                    "name": "Ergonomic Hooks",
                    "url": "https://www.crochet.com/ergonomic-hooks/c/500304"
                },
                {
                    "name": "Tunisian Hooks",
                    "url": "https://www.crochet.com/hooks/tunisian-hooks/c/500312"
                },
                {
                    "name": "View All",
                    "url": "https://www.crochet.com/hooks/view-all-hooks/c/500397"
                }
            ]
        },
        {
            "name": "Patterns",
            "subcategories": [
                {
                    "name": "New",
                    "url": "https://www.crochet.com/patterns/new/c/500220"
                },
                {
                    "name": "Free Patterns",
                    "url": "https://www.crochet.com/patterns/free-crochet-patterns/c/500250"
                },
                {
                    "name": "Winter Holiday Patterns",
                    "url": "https://www.crochet.com/patterns/winter-holiday-patterns/c/50025236"
                },
                {
                    "name": "View All",
                    "url": "https://www.crochet.com/patterns/view-all/c/500298"
                }
            ]
        }
    ]
}